Metadata-Version: 2.0
Name: supervisor-healthcheck
Version: 0.8.0
Summary: Framework to build health checks for Supervisor-based services, based on supervisor-checks
Home-page: https://github.com/caio2k/supervisor_checks
Author: caio2k
Author-email: caio2k@gmail.com
License: MIT
Download-URL: https://github.com/caio2k/supervisor_checks/tarball/0.8.0
Keywords: supervisor,event,listener,eventlistener,http,memory,xmlrpc,health,check,monitor,cpu
Platform: UNKNOWN
Classifier: License :: OSI Approved :: MIT License
Classifier: Development Status :: 4 - Beta
Classifier: Intended Audience :: Developers
Classifier: Operating System :: POSIX
Classifier: Topic :: System :: Boot
Classifier: Topic :: System :: Monitoring
Classifier: Topic :: System :: Systems Administration
Classifier: Programming Language :: Python
Classifier: Programming Language :: Python :: 2
Classifier: Programming Language :: Python :: 2.6
Classifier: Programming Language :: Python :: 2.7
Classifier: Programming Language :: Python :: 3
Classifier: Programming Language :: Python :: 3.2
Classifier: Programming Language :: Python :: 3.3
Classifier: Programming Language :: Python :: 3.4
Requires-Dist: futures
Requires-Dist: netifaces
Requires-Dist: psutil
Requires-Dist: supervisor (>=3.0.0)
Provides-Extra: test
Requires-Dist: futures; extra == 'test'
Requires-Dist: netifaces; extra == 'test'
Requires-Dist: psutil; extra == 'test'
Requires-Dist: supervisor (>=3.0.0); extra == 'test'
